{"sections":{"main":{"type":"main-page","settings":{}},"2c7eec80-b410-4fc4-9c17-966f996a87cd":{"type":"about-us-banner","settings":{"heading":"<span>Experience comfort and functionality like never before with our  products.<\/span> Our passion for quality & customer satisfaction drives everything we do.\"","banerimg":"shopify:\/\/shop_images\/Rectangle_13_2.png","mobimage":"shopify:\/\/shop_images\/Rectangle_13_3.png"}},"19f6220a-48c0-479f-94aa-aed85a80b06d":{"type":"text-and-image","settings":{"image":"shopify:\/\/shop_images\/Rectangle_341_1.png","image_mask":"none","image2":"shopify:\/\/shop_images\/Rectangle_342_1.png","image2_mask":"none","subtitle":"","title":"vision & mission","text1":"“High-quality products for outdoor enthusiasts.","text":"<p>Committed to sustainability, exceptional service, and continuous improvement.”<\/p><p>At our company, we are passionate about providing high-quality products that enhance the comfort, convenience, and safety of outdoor enthusiasts. Our vision is to design Chest Vest products that meet the unique needs of our customers, while our mission is to use sustainable materials and provide exceptional customer service. <\/p>","button_label":"","button_link":"","button_style":"primary","align_text":"left","image_width":"50","layout":"right","divider":false,"top_padding":true,"bottom_padding":true,"lazyload_images":true}},"ac03eb4a-0fb4-4578-b1da-1dd5b4c3d224":{"type":"text-and-image","settings":{"image_mask":"none","image2_mask":"none","subtitle":"","title":"Image with text","text1":"","text":"<p>Pair large text with an image to tell a story, explain a detail about your product, or describe a new promotion.<\/p>","button_label":"","button_link":"","button_style":"primary","align_text":"left","image_width":"50","layout":"left","divider":false,"top_padding":true,"bottom_padding":true,"lazyload_images":true}},"2b17c23c-52f9-40df-bdbf-468b4cd5b9db":{"type":"logo-list","blocks":{"template--18875835908384__2b17c23c-52f9-40df-bdbf-468b4cd5b9db-1685058799f8e70d9d-0":{"type":"logo_image","settings":{"image":"shopify:\/\/shop_images\/Group_4078.png","link":""}},"template--18875835908384__2b17c23c-52f9-40df-bdbf-468b4cd5b9db-1685058799f8e70d9d-1":{"type":"logo_image","settings":{"image":"shopify:\/\/shop_images\/Group_4082.png","link":""}},"template--18875835908384__2b17c23c-52f9-40df-bdbf-468b4cd5b9db-1685058799f8e70d9d-2":{"type":"logo_image","settings":{"image":"shopify:\/\/shop_images\/Group_4076.png","link":""}},"template--18875835908384__2b17c23c-52f9-40df-bdbf-468b4cd5b9db-1685058799f8e70d9d-3":{"type":"logo_image","settings":{"image":"shopify:\/\/shop_images\/Group_4075_f8c35dd4-6b1c-4732-b7f0-f95438a8e8da.png","link":""}},"ed34d908-4320-4391-ad10-878459dbc027":{"type":"logo_image","settings":{"image":"shopify:\/\/shop_images\/Group_4081.png","link":""}},"5382cf36-2ee4-43bf-8031-84f0cfdbc050":{"type":"logo_image","settings":{"image":"shopify:\/\/shop_images\/Group_4082.png","link":""}},"09783cdb-5b91-42bc-82ed-fd1cce4e5124":{"type":"logo_image","settings":{"image":"shopify:\/\/shop_images\/Group_4076.png","link":""}},"7774a4e1-c6c4-47a0-8bca-e0d41a9b793f":{"type":"logo_image","settings":{"image":"shopify:\/\/shop_images\/Group_4075.png","link":""}}},"block_order":["template--18875835908384__2b17c23c-52f9-40df-bdbf-468b4cd5b9db-1685058799f8e70d9d-0","template--18875835908384__2b17c23c-52f9-40df-bdbf-468b4cd5b9db-1685058799f8e70d9d-1","template--18875835908384__2b17c23c-52f9-40df-bdbf-468b4cd5b9db-1685058799f8e70d9d-2","template--18875835908384__2b17c23c-52f9-40df-bdbf-468b4cd5b9db-1685058799f8e70d9d-3","ed34d908-4320-4391-ad10-878459dbc027","5382cf36-2ee4-43bf-8031-84f0cfdbc050","09783cdb-5b91-42bc-82ed-fd1cce4e5124","7774a4e1-c6c4-47a0-8bca-e0d41a9b793f"],"settings":{"title":"OUR CLIENTS","logo_opacity":100,"divider":false,"btnname":"Read more","btnlink":"#"}},"870793ef-d07f-46f1-aef8-6b0c897282ff":{"type":"text-columns","disabled":true,"blocks":{"template--18875835908384__870793ef-d07f-46f1-aef8-6b0c897282ff-1685059675e5d72f04-0":{"type":"text_block","settings":{"enable_image":true,"image":"shopify:\/\/shop_images\/Rectangle_358.png","image_mask":"none","image_width":650,"title":"Joseph Chang","text":"<p>CEO\/Co-founder<\/p>","button_label":"","button_link":""}},"template--18875835908384__870793ef-d07f-46f1-aef8-6b0c897282ff-1685059675e5d72f04-1":{"type":"text_block","settings":{"enable_image":true,"image":"shopify:\/\/shop_images\/Rectangle_359.png","image_mask":"none","image_width":650,"title":"Kane Davidson","text":"<p>CFO\/Co-founder<\/p>","button_label":"","button_link":""}},"template--18875835908384__870793ef-d07f-46f1-aef8-6b0c897282ff-1685059675e5d72f04-2":{"type":"text_block","settings":{"enable_image":true,"image":"shopify:\/\/shop_images\/Rectangle_360.png","image_mask":"none","image_width":650,"title":"Malinda Hope","text":"<p>CMO\/Co-founder<\/p>","button_label":"","button_link":""}}},"block_order":["template--18875835908384__870793ef-d07f-46f1-aef8-6b0c897282ff-1685059675e5d72f04-0","template--18875835908384__870793ef-d07f-46f1-aef8-6b0c897282ff-1685059675e5d72f04-1","template--18875835908384__870793ef-d07f-46f1-aef8-6b0c897282ff-1685059675e5d72f04-2"],"settings":{"subhead":"Founders","title":"Look back at our founders","textt":"Meet the team behind our high-quality products. Committed to sustainability, exceptional service, and continuous improvement, our team is driven by a passion for outdoor adventure. Join with us !!!","align_text":"left","divider":false}},"2e8dfba8-b526-423e-9099-648564a7942a":{"type":"instagram","settings":{"heading":"Join Our Community on Instagram!!!","para":"Join our Chest Vest community on Instagram for behind-the-scenes access, outdoor inspiration, and the latest news and promotions.","btnname":"Follow Us","btnlik":"#","firstimage":"shopify:\/\/shop_images\/Rectangle_362.png","scndimage":"shopify:\/\/shop_images\/Rectangle_363.png","thirdimage":"shopify:\/\/shop_images\/Rectangle_364.png","fourthimage":"shopify:\/\/shop_images\/Rectangle_365.png","fifthimage":"shopify:\/\/shop_images\/Rectangle_366.png","sixthimage":"shopify:\/\/shop_images\/Rectangle_367.png","svnthimage":"shopify:\/\/shop_images\/Rectangle_368.png"}},"8d387ff0-22df-4d51-826b-2435b43ed977":{"type":"promo-grid","blocks":{"template--18875835908384__8d387ff0-22df-4d51-826b-2435b43ed977-16850586008e751ea2-0":{"type":"advanced","settings":{"subheading":"Learn more","heading":"our manufacturing process","textarea":"At our company, we take great pride in our manufacturing process. From design and prototyping to sourcing materials and quality control, we pay strict attention to detail and quality to ensure that every product meets the high standards our customers expect.","cta_text1":"Watch the video","cta_link1":"","cta_text2":"","cta_link2":"","image":"shopify:\/\/shop_images\/video-backgroundimage.png","video_url":"https:\/\/cdn.shopify.com\/videos\/c\/o\/v\/1272c144549b4315ad0e489de29f0a20.mp4","width":"100","height":500,"text_size":100,"text_align":"vertical-center horizontal-center","color_accent":"rgba(0,0,0,0)","boxed":false,"framed":false}}},"block_order":["template--18875835908384__8d387ff0-22df-4d51-826b-2435b43ed977-16850586008e751ea2-0"],"settings":{"full_width":true,"gutter_size":0,"space_above":true,"space_below":true,"lazyload_images":true}},"form":{"type":"contact-form","settings":{"title":"Contact us","text":"","head1":"INDIA","adres1":"INDIAUdyog Vihar Phase 4, Sector 37, Gurugram, 122001,Haryana, India","mob1":"+91-9871657338, +91-7999999735","email1":"sales@98fahren.com","head2":"USA","adres2":"5845 W Willis ave, Fresno, 5845 W Willis ave, Fresno CA 93722, USA","mob2":"00 1 (209) 988-9142","email2":"sales@98fahren.com","show_phone":true,"narrow_column":true}},"fb1b78e7-156c-40ea-9515-cf649ab794e3":{"type":"countdown","disabled":true,"blocks":{"template--18875835908384__fb1b78e7-156c-40ea-9515-cf649ab794e3-16861951241ef0eb0f-0":{"type":"content","settings":{"heading":"BLACK FRIDAY SALE","heading_size":"h2","text":"<p>20% OFF ON ALL PRODUCTS<\/p>","content_alignment":"left"}},"template--18875835908384__fb1b78e7-156c-40ea-9515-cf649ab794e3-16861951241ef0eb0f-1":{"type":"timer","settings":{"year":"2025","month":"01","day":"1","hour":"03","minute":"00","hide_timer":false,"text":""}},"template--18875835908384__fb1b78e7-156c-40ea-9515-cf649ab794e3-16861951241ef0eb0f-2":{"type":"button","settings":{"button_link":"","button":"Shop Now","button_style":"solid"}}},"block_order":["template--18875835908384__fb1b78e7-156c-40ea-9515-cf649ab794e3-16861951241ef0eb0f-0","template--18875835908384__fb1b78e7-156c-40ea-9515-cf649ab794e3-16861951241ef0eb0f-1","template--18875835908384__fb1b78e7-156c-40ea-9515-cf649ab794e3-16861951241ef0eb0f-2"],"settings":{"layout":"banner","full_width":true,"text_color":"#000000","background_color":"#f6f7fa","overlay_color":"#000000","overlay_opacity":0,"lazyload_images":true}},"af3e0b7b-8157-4025-adb6-66fbdbbc4d7e":{"type":"text-with-icons","disabled":true,"blocks":{"template--18875835908384__af3e0b7b-8157-4025-adb6-66fbdbbc4d7e-16861952223a56425a-0":{"type":"text_block","settings":{"iconsimgs":"shopify:\/\/shop_images\/100_4c9ebe1e-6323-4120-961e-f67497668d28.png","icon":"chat","title":"100% polyester wicking fabric","text":"<p>Polyester wicking fabric keeps you dry during activities by wicking moisture away from the skin.<\/p>"}},"template--18875835908384__af3e0b7b-8157-4025-adb6-66fbdbbc4d7e-16861952223a56425a-1":{"type":"text_block","settings":{"iconsimgs":"shopify:\/\/shop_images\/secure-payment.png","icon":"chat","title":"Secure payment","text":"<p>We use secure payment methods to protect your personal and financial information.<\/p>"}},"template--18875835908384__af3e0b7b-8157-4025-adb6-66fbdbbc4d7e-16861952223a56425a-2":{"type":"text_block","settings":{"iconsimgs":"shopify:\/\/shop_images\/secure-payment_385b0f22-7571-461b-957c-6f720bc58e64.png","icon":"chat","title":"Secure payment","text":"<p>We use secure payment methods to protect your personal and financial information.<\/p>"}},"61555187-68ad-49b4-8f85-e4d8d13bea10":{"type":"text_block","settings":{"iconsimgs":"shopify:\/\/shop_images\/fast-delivery.png","icon":"chat","title":"Fast delivery","text":"<p>We offer express delivery options to ensure your order is delivered quickly and efficiently.<\/p>"}}},"block_order":["template--18875835908384__af3e0b7b-8157-4025-adb6-66fbdbbc4d7e-16861952223a56425a-0","template--18875835908384__af3e0b7b-8157-4025-adb6-66fbdbbc4d7e-16861952223a56425a-1","template--18875835908384__af3e0b7b-8157-4025-adb6-66fbdbbc4d7e-16861952223a56425a-2","61555187-68ad-49b4-8f85-e4d8d13bea10"],"settings":{"title":"","align_text":"center","desktop_columns_per_row":4,"icon_color":"#000000","button_label":"","button_link":"","divider":false}}},"order":["main","2c7eec80-b410-4fc4-9c17-966f996a87cd","19f6220a-48c0-479f-94aa-aed85a80b06d","ac03eb4a-0fb4-4578-b1da-1dd5b4c3d224","2b17c23c-52f9-40df-bdbf-468b4cd5b9db","870793ef-d07f-46f1-aef8-6b0c897282ff","2e8dfba8-b526-423e-9099-648564a7942a","8d387ff0-22df-4d51-826b-2435b43ed977","form","fb1b78e7-156c-40ea-9515-cf649ab794e3","af3e0b7b-8157-4025-adb6-66fbdbbc4d7e"]}